{
	"title": "Stuff",
	"tab": "Stuff",
	"list": {
		"description": "Here are various things I've made",
		"items": [
			{
				"title": "Games",
				"description": "This is a bunch of games or \"toys\" that I've made for fun.",
				"list": {
					"description": "This is a bunch of games or \"toys\" that I've made for fun.",
					"items": [
						{
							"title": "Psycosnake",
							"description": "A snake clone with pretty colors.",
							"url": "/view/singles/Psychosnake.html",
							"icon": "map"
						}, {
							"title": "Dodge",
							"description": "A 3D arcade game that never happened",
							"url": "/singles/Dodge.html",
							"icon": "rocket"
						}
					]
				},
				"url": "/games",
				"icon": "gamepad"
			}, {
				"title": "Tools",
				"description": "These are some useful tools for performing various tasks",
				"list": {
					"description": "These are some useful tools for performing various tasks",
					"items": [
						{
							"title": "Flash Cards",
							"description": "A tool that can be used to help memorize things. Record question - answer pairs",
							"url": "/view/singles/FlashCards.html",
							"icon": "book"
						}, {
							"title": "Soundz",
							"description": "A toy for generating sounds with an Oscillator in your browser. Open several windows and jam out.",
							"url": "/view/singles/Soundz.html",
							"icon": "music"
						}, {
							"title": "SVG Test",
							"description": "This can be used to test making SVG images, it lets you view the SVG image you're working on on the right of the page.",
							"url": "/view/singles/SVG-Test.html",
							"icon": "photo"
						}, {
							"title": "Random From List",
							"description": "Chooses one item from a list specified",
							"url": "/view/singles/RandomFromList.html",
							"icon": "tasks"
						}, {
							"title": "Random Remove",
							"description": "Removes a random item from a list until there are none left",
							"url": "/view/singles/RandomRemover.html",
							"icon": "tasks"
						}, {
							"title": "List Randomizer",
							"description": "Shuffles a list of items in a random fashion",
							"url": "/view/singles/ListRandomizer.html",
							"icon": "tasks"
						}
					]
				},
				"url": "/tools",
				"icon": "wrench"
			}, {
				"title": "Userscripts",
				"description": "These are single file plugins that let you do various things.",
				"list": {
					"description": "These are single file plugins that let you do various things.",
					"items": [
						{
							"title": "Autopoke",
							"description": "This automatically responds to pokes on Facebook for you. ",
							"url": "/userscripts/Autopoke.user.js",
							"icon": "right hand"
						},
						{
							"title": "XKCD News Substitutions",
							"description": "This does some word substitutions that make news stories more fun to read.",
							"url": "/userscript/XKCD1288.user.js",
							"icon": "browser"
						},
						{
							"title": "No Typing Notifications",
							"description": "This gives you a more stealthy Facebook chat experience by blocking people from seeing the \"seen\" and \"typing\" notifications.",
							"url": "/userscripts/NoTypeNotify.user.js",
							"icon": "chat"
						}
					]
				},
				"url": "/userscripts",
				"icon": "puzzle piece"
			}
		]
	}
}
